quantum_platform/__init__.py
quantum_platform/app.py
quantum_platform/assets/量子力学界面图.jpg
quantum_platform-0.2.9.dist-info/licenses/LICENSE
quantum_platform-0.2.9.dist-info/METADATA
quantum_platform-0.2.9.dist-info/WHEEL
quantum_platform-0.2.9.dist-info/entry_points.txt
quantum_platform-0.2.9.dist-info/top_level.txt
quantum_platform-0.2.9.dist-info/RECORD
