Metadata-Version: 2.4
Name: quantum_platform
Version: 0.2.9
Summary: 量子力学教学仿真平台（Flet + PINN）
Author: Your Name
Author-email: you@example.com
Classifier: Programming Language :: Python :: 3
Classifier: Operating System :: OS Independent
Requires-Python: >=3.8
License-File: LICENSE
Requires-Dist: flet>=0.7.0
Requires-Dist: matplotlib
Requires-Dist: scipy
Requires-Dist: numpy
Requires-Dist: plotly
Requires-Dist: torch
Requires-Dist: scikit-image
Dynamic: author
Dynamic: author-email
Dynamic: classifier
Dynamic: description
Dynamic: description-content-type
Dynamic: license-file
Dynamic: requires-dist
Dynamic: requires-python
Dynamic: summary
